[
  {
    "inputs": [
      {
        "internalType": "address",
        "name": "_user",
        "type": "address"
      },
      {
        "internalType": "uint256",
        "name": "Amount",
        "type": "uint256"
      }
    ],
    "name": "BuyTicket",
    "outputs": [],
    "stateMutability": "nonpayable",
    "type": "function"
  },
  {
    "inputs": [
      {
        "internalType": "address",
        "name": "_user",
        "type": "address"
      }
    ],
    "name": "getTicketNumber",
    "outputs": [
      {
        "internalType": "uint256",
        "name": "",
        "type": "uint256"
      }
    ],
    "stateMutability": "nonpayable",
    "type": "function"
  },
  {
    "inputs": [
      {
        "internalType": "address",
        "name": "_user",
        "type": "address"
      },
      {
        "internalType": "uint256",
        "name": "Amount",
        "type": "uint256"
      }
    ],
    "name": "UseTicket",
    "outputs": [],
    "stateMutability": "nonpayable",
    "type": "function"
  },
  {
    "inputs": [
      {
        "internalType": "address",
        "name": "",
        "type": "address"
      }
    ],
    "name": "_TicketHolders",
    "outputs": [
      {
        "internalType": "uint256",
        "name": "",
        "type": "uint256"
      }
    ],
    "stateMutability": "view",
    "type": "function"
  }
]